[{
  "_id": {
    "$oid": "600aef995d49cb12ecfb4fcd"
  },
  "joueurs": [],
  "tableau": {
    "$oid": "5fbc43b767e5cb1050ab0443"
  },
  "locked": false,
  "__v": 0
},{
  "_id": {
    "$oid": "600aef9c5d49cb12ecfb4fce"
  },
  "joueurs": [],
  "tableau": {
    "$oid": "5fbc43b767e5cb1050ab0443"
  },
  "locked": false,
  "__v": 0
},{
  "_id": {
    "$oid": "600aef9e5d49cb12ecfb4fcf"
  },
  "joueurs": [],
  "tableau": {
    "$oid": "5fbc43b767e5cb1050ab0443"
  },
  "locked": false,
  "__v": 0
},{
  "_id": {
    "$oid": "600aefa05d49cb12ecfb4fd0"
  },
  "joueurs": [],
  "tableau": {
    "$oid": "5fbc43b767e5cb1050ab0443"
  },
  "locked": false,
  "__v": 0
},{
  "_id": {
    "$oid": "600aefa55d49cb12ecfb4fd1"
  },
  "joueurs": [],
  "tableau": {
    "$oid": "5fbc43b767e5cb1050ab0443"
  },
  "locked": false,
  "__v": 0
},{
  "_id": {
    "$oid": "600af3c0a8bfea37a42c63fd"
  },
  "joueurs": [],
  "tableau": {
    "$oid": "5fbc43b767e5cb1050ab0443"
  },
  "locked": false,
  "__v": 0
},{
  "_id": {
    "$oid": "600af457a8bfea37a42c63fe"
  },
  "joueurs": [],
  "tableau": {
    "$oid": "5fbc43b767e5cb1050ab0443"
  },
  "locked": false,
  "__v": 0
},{
  "_id": {
    "$oid": "600af4baa8bfea37a42c63ff"
  },
  "joueurs": [],
  "tableau": {
    "$oid": "5ffe3413345fda3c709c8075"
  },
  "locked": false,
  "__v": 0
},{
  "_id": {
    "$oid": "600af4baa8bfea37a42c6400"
  },
  "joueurs": [],
  "tableau": {
    "$oid": "5ffe3413345fda3c709c8075"
  },
  "locked": false,
  "__v": 0
},{
  "_id": {
    "$oid": "600af4baa8bfea37a42c6401"
  },
  "joueurs": [],
  "tableau": {
    "$oid": "5ffe3413345fda3c709c8075"
  },
  "locked": false,
  "__v": 0
},{
  "_id": {
    "$oid": "600af4baa8bfea37a42c6402"
  },
  "joueurs": [],
  "tableau": {
    "$oid": "5ffe3413345fda3c709c8075"
  },
  "locked": false,
  "__v": 0
},{
  "_id": {
    "$oid": "600af4baa8bfea37a42c6403"
  },
  "joueurs": [],
  "tableau": {
    "$oid": "5ffe3413345fda3c709c8075"
  },
  "locked": false,
  "__v": 0
},{
  "_id": {
    "$oid": "600af4baa8bfea37a42c6404"
  },
  "joueurs": [],
  "tableau": {
    "$oid": "5ffe3413345fda3c709c8075"
  },
  "locked": false,
  "__v": 0
},{
  "_id": {
    "$oid": "600af4baa8bfea37a42c6405"
  },
  "joueurs": [],
  "tableau": {
    "$oid": "5ffe3413345fda3c709c8075"
  },
  "locked": false,
  "__v": 0
},{
  "_id": {
    "$oid": "600af4baa8bfea37a42c6406"
  },
  "joueurs": [],
  "tableau": {
    "$oid": "5ffe3413345fda3c709c8075"
  },
  "locked": false,
  "__v": 0
},{
  "_id": {
    "$oid": "600af4bca8bfea37a42c6407"
  },
  "joueurs": [],
  "tableau": {
    "$oid": "5fbc43b767e5cb1050ab0444"
  },
  "locked": false,
  "__v": 0
},{
  "_id": {
    "$oid": "600af4bca8bfea37a42c6408"
  },
  "joueurs": [],
  "tableau": {
    "$oid": "5fbc43b767e5cb1050ab0444"
  },
  "locked": false,
  "__v": 0
},{
  "_id": {
    "$oid": "600af4bca8bfea37a42c6409"
  },
  "joueurs": [],
  "tableau": {
    "$oid": "5fbc43b767e5cb1050ab0444"
  },
  "locked": false,
  "__v": 0
},{
  "_id": {
    "$oid": "600af4bca8bfea37a42c640a"
  },
  "joueurs": [],
  "tableau": {
    "$oid": "5fbc43b767e5cb1050ab0444"
  },
  "locked": false,
  "__v": 0
},{
  "_id": {
    "$oid": "600af4bca8bfea37a42c640b"
  },
  "joueurs": [],
  "tableau": {
    "$oid": "5fbc43b767e5cb1050ab0444"
  },
  "locked": false,
  "__v": 0
},{
  "_id": {
    "$oid": "600af4bca8bfea37a42c640c"
  },
  "joueurs": [],
  "tableau": {
    "$oid": "5fbc43b767e5cb1050ab0444"
  },
  "locked": false,
  "__v": 0
},{
  "_id": {
    "$oid": "600af4bca8bfea37a42c640d"
  },
  "joueurs": [],
  "tableau": {
    "$oid": "5fbc43b767e5cb1050ab0444"
  },
  "locked": false,
  "__v": 0
},{
  "_id": {
    "$oid": "600af4bca8bfea37a42c640e"
  },
  "joueurs": [],
  "tableau": {
    "$oid": "5fbc43b767e5cb1050ab0444"
  },
  "locked": false,
  "__v": 0
}]